circlejerk-0.2.0.dist-info/METADATA
circlejerk-0.2.0.dist-info/WHEEL
circlejerk/__init__.py
circlejerk/circlejerk.abi3.so
circlejerk-0.2.0.dist-info/RECORD
