Metadata-Version: 2.4
Name: circlejerk
Version: 0.2.0
Summary: Fit a circle on a mask as accurately as possible by brute-forcing a location from an approximate location
Author: Peter Evers <peter@tetmet.com>
Author-email: Peter Evers <peter@tetmet.com>
License: MIT
